cortex/__init__.py
cortex/api_key_detector.py
cortex/ask.py
cortex/branding.py
cortex/cli.py
cortex/config_manager.py
cortex/config_utils.py
cortex/context_memory.py
cortex/coordinator.py
cortex/demo.py
cortex/dependency_check.py
cortex/dependency_importer.py
cortex/dependency_resolver.py
cortex/doctor.py
cortex/env_loader.py
cortex/env_manager.py
cortex/error_parser.py
cortex/first_run_wizard.py
cortex/graceful_degradation.py
cortex/hardware_detection.py
cortex/hwprofiler.py
cortex/install_parallel.py
cortex/installation_history.py
cortex/installation_verifier.py
cortex/llm_router.py
cortex/logging_system.py
cortex/network_config.py
cortex/notification_manager.py
cortex/packages.py
cortex/parallel_llm.py
cortex/permission_manager.py
cortex/progress_indicators.py
cortex/progress_tracker.py
cortex/role_manager.py
cortex/semantic_cache.py
cortex/shell_env_analyzer.py
cortex/shell_installer.py
cortex/shell_integration.py
cortex/stack_manager.py
cortex/transaction_history.py
cortex/validators.py
cortex/kernel_features/__init__.py
cortex/kernel_features/accelerator_limits.py
cortex/kernel_features/hardware_detect.py
cortex/kernel_features/kv_cache_manager.py
cortex/kernel_features/llm_device.py
cortex/kernel_features/model_lifecycle.py
cortex/kernel_features/ebpf/__init__.py
cortex/kernel_features/ebpf/cortex_sched_loader.py
cortex/llm/__init__.py
cortex/llm/interpreter.py
cortex/sandbox/__init__.py
cortex/sandbox/docker_sandbox.py
cortex/sandbox/sandbox_example.py
cortex/sandbox/sandbox_executor.py
cortex/utils/__init__.py
cortex/utils/commands.py
cortex/utils/db_pool.py
cortex_linux-0.1.0.dist-info/licenses/LICENSE
cortex_linux-0.1.0.dist-info/METADATA
cortex_linux-0.1.0.dist-info/WHEEL
cortex_linux-0.1.0.dist-info/entry_points.txt
cortex_linux-0.1.0.dist-info/top_level.txt
cortex_linux-0.1.0.dist-info/RECORD
