Metadata-Version: 2.4
Name: cortex-linux
Version: 0.1.0
Summary: AI-powered package manager for Debian/Ubuntu that understands natural language
Author-email: Cortex Linux <mike@cortexlinux.com>
Maintainer-email: Mike Morgan <mike@cortexlinux.com>
License-Expression: Apache-2.0
Project-URL: Homepage, https://github.com/cortexlinux/cortex
Project-URL: Documentation, https://cortexlinux.com/docs
Project-URL: Repository, https://github.com/cortexlinux/cortex.git
Project-URL: Issues, https://github.com/cortexlinux/cortex/issues
Project-URL: Discussions, https://github.com/cortexlinux/cortex/discussions
Project-URL: Changelog, https://github.com/cortexlinux/cortex/blob/main/CHANGELOG.md
Keywords: linux,package-manager,ai,llm,natural-language,apt,debian,ubuntu,cli
Classifier: Development Status :: 3 - Alpha
Classifier: Environment :: Console
Classifier: Intended Audience :: Developers
Classifier: Intended Audience :: System Administrators
Classifier: Topic :: System :: Installation/Setup
Classifier: Topic :: System :: Systems Administration
Classifier: Topic :: Software Development :: Libraries :: Python Modules
Classifier: Programming Language :: Python :: 3
Classifier: Programming Language :: Python :: 3.10
Classifier: Programming Language :: Python :: 3.11
Classifier: Programming Language :: Python :: 3.12
Classifier: Operating System :: POSIX :: Linux
Classifier: Typing :: Typed
Requires-Python: >=3.10
License-File: LICENSE
Requires-Dist: anthropic>=0.18.0
Requires-Dist: openai>=1.0.0
Requires-Dist: requests>=2.32.4
Requires-Dist: pyyaml>=6.0.0
Requires-Dist: python-dotenv>=1.0.0
Requires-Dist: cryptography>=42.0.0
Requires-Dist: rich>=13.0.0
Requires-Dist: typing-extensions>=4.0.0
Provides-Extra: dev
Requires-Dist: pytest>=7.0.0; extra == "dev"
Requires-Dist: pytest-cov>=4.0.0; extra == "dev"
Requires-Dist: pytest-asyncio>=0.23.0; extra == "dev"
Requires-Dist: pytest-mock>=3.12.0; extra == "dev"
Requires-Dist: pytest-timeout>=2.3.0; extra == "dev"
Requires-Dist: black>=24.0.0; extra == "dev"
Requires-Dist: ruff>=0.8.0; extra == "dev"
Requires-Dist: mypy>=1.0.0; extra == "dev"
Requires-Dist: pre-commit>=3.0.0; extra == "dev"
Requires-Dist: isort>=5.0.0; extra == "dev"
Requires-Dist: build>=0.10.0; extra == "dev"
Provides-Extra: security
Requires-Dist: bandit>=1.7.0; extra == "security"
Requires-Dist: safety>=2.0.0; extra == "security"
Provides-Extra: docs
Requires-Dist: mkdocs>=1.5.0; extra == "docs"
Requires-Dist: mkdocs-material>=9.0.0; extra == "docs"
Requires-Dist: mkdocstrings[python]>=0.24.0; extra == "docs"
Provides-Extra: all
Requires-Dist: cortex-linux[dev,docs,security]; extra == "all"
Dynamic: license-file
